LICENSE.txt
MANIFEST.in
README.md
requirements.txt
setup.cfg
setup.py
cheesy/__init__.py
cheesy/ch.py
cheesy.egg-info/PKG-INFO
cheesy.egg-info/SOURCES.txt
cheesy.egg-info/dependency_links.txt
cheesy.egg-info/entry_points.txt
cheesy.egg-info/requires.txt
cheesy.egg-info/top_level.txt