Metadata-Version: 1.1
Name: cheesy
Version: 0.0.1
Summary: cheesy gives you all the information for today's cheese shop pipy factory.
Home-page: https://github.com/arindampradhan/cheesy
Author: Arindam Pradhan
Author-email: arindampradhan10@gmail.com
License: MIT
Download-URL: https://github.com/arindampradhan/cheesy/archive/v0.0.1.tar.gz
Keywords: pipy,information,packages
Platform: UNKNOWN
